pyfront/__init__.py
pyfront/core.py
pyfronter-0.1.0.dist-info/licenses/LICENSE
pyfronter-0.1.0.dist-info/METADATA
pyfronter-0.1.0.dist-info/WHEEL
pyfronter-0.1.0.dist-info/top_level.txt
pyfronter-0.1.0.dist-info/RECORD
