Metadata-Version: 2.4
Name: pyfronter
Version: 0.1.0
Summary: pyfronter is a modern, Python-based frontend framework designed to simplify web development. With a focus on modularity and ease of use, pyfronter helps developers build scalable and maintainable web applications quickly.
Author-email: RedSnows <id.suzuya@gmail.com>
License: MIT
Requires-Python: >=3.7
License-File: LICENSE
Requires-Dist: colorama
Dynamic: license-file
